bump_dependencies.py
test_bump_dependencies.py
bump_dependencies-0.1.2.dist-info/licenses/LICENSE
bump_dependencies-0.1.2.dist-info/METADATA
bump_dependencies-0.1.2.dist-info/WHEEL
bump_dependencies-0.1.2.dist-info/entry_points.txt
bump_dependencies-0.1.2.dist-info/top_level.txt
bump_dependencies-0.1.2.dist-info/RECORD
