Metadata-Version: 2.4
Name: bump-dependencies
Version: 0.1.2
Summary: Bump Python package dependencies in pyproject.toml
Author: Corey Goldberg
Maintainer: Corey Goldberg
License-Expression: MIT
Project-URL: homepage, https://github.com/cgoldberg/bump-dependencies
Project-URL: source, https://github.com/cgoldberg/bump-dependencies
Project-URL: download, https://pypi.org/project/bump-dependencies
Keywords: package,dependencies,requirements,bump,upgrade
Classifier: Environment :: Console
Classifier: Intended Audience :: Developers
Classifier: Programming Language :: Python
Classifier: Programming Language :: Python :: 3
Classifier: Programming Language :: Python :: 3.10
Classifier: Programming Language :: Python :: 3.11
Classifier: Programming Language :: Python :: 3.12
Classifier: Programming Language :: Python :: 3.13
Classifier: Programming Language :: Python :: 3.14
Requires-Python: >=3.9
License-File: LICENSE
Requires-Dist: packaging==25.0
Requires-Dist: requests==2.32.5
Requires-Dist: requirements-parser==0.13.0
Requires-Dist: rich==14.2.0
Requires-Dist: tomlkit==0.13.3
Requires-Dist: validate-pyproject==0.24.1
Dynamic: license-file
